odino/__init__.py
odino/cli.py
odino/indexer.py
odino/searcher.py
odino/utils.py
odino-0.1.4.dist-info/licenses/LICENSE
odino-0.1.4.dist-info/METADATA
odino-0.1.4.dist-info/WHEEL
odino-0.1.4.dist-info/entry_points.txt
odino-0.1.4.dist-info/top_level.txt
odino-0.1.4.dist-info/RECORD
