Metadata-Version: 2.4
Name: odino
Version: 0.1.4
Summary: Local semantic search CLI tool for codebases using embeddings
Home-page: https://github.com/cesp99/odino
Author: Carlo Esposito
Author-email: Carlo Esposito <carlo@aploi.de>
License: GPL-3.0-only
Project-URL: Homepage, https://github.com/cesp99/odino
Project-URL: Repository, https://github.com/cesp99/odino
Project-URL: Issues, https://github.com/cesp99/odino/issues
Classifier: Development Status :: 4 - Beta
Classifier: Intended Audience :: Developers
Classifier: Programming Language :: Python :: 3
Classifier: Programming Language :: Python :: 3.11
Classifier: Programming Language :: Python :: 3.12
Classifier: Topic :: Software Development :: Libraries :: Python Modules
Classifier: Topic :: Text Processing :: Indexing
Classifier: Topic :: Utilities
Requires-Python: >=3.11
License-File: LICENSE
Requires-Dist: typer>=0.9.0
Requires-Dist: chromadb>=0.4.0
Requires-Dist: sentence-transformers>=2.2.0
Requires-Dist: rich>=13.0.0
Requires-Dist: tqdm>=4.64.0
Requires-Dist: numpy>=1.24.0
Requires-Dist: pathspec>=0.11.0
Dynamic: author
Dynamic: home-page
Dynamic: license-file
Dynamic: requires-python
